gajo_utils/__init__.py
gajo_utils/decorators.py
gajo_utils/errors.py
gajo_utils/middleware.py
gajo_utils/utils.py
gajo_utils/management/__init__.py
gajo_utils/management/commands/__init__.py
gajo_utils/management/commands/dumpfixtures.py
gajo_utils/management/commands/loadfixtures.py
gajo_utils/management/commands/testsingle.py
django_gajo_utils-0.1.0.dist-info/LICENSE
django_gajo_utils-0.1.0.dist-info/METADATA
django_gajo_utils-0.1.0.dist-info/WHEEL
django_gajo_utils-0.1.0.dist-info/top_level.txt
django_gajo_utils-0.1.0.dist-info/RECORD
