Metadata-Version: 2.1
Name: django-gajo-utils
Version: 0.1.0
Summary: Utilities for Django project.
Author-email: jozekuhar <joze.kuhar@gajogroup.com>
License: MIT
Project-URL: Source, https://github.com/jozekuhar/django-gajo-utils.git
Requires-Python: >=3.9
License-File: LICENSE
Provides-Extra: dev
Requires-Dist: build>=1.2.2; extra == "dev"
Requires-Dist: twine>=5.1.1; extra == "dev"
Requires-Dist: pytest-cov>=5.0.0; extra == "dev"
Requires-Dist: pytest-django>=4.9.0; extra == "dev"
Requires-Dist: coverage>=7.6.1; extra == "dev"
Requires-Dist: ruff>=0.6.4; extra == "dev"
Requires-Dist: pre-commit>=v3.8.0; extra == "dev"
